LICENSE
MANIFEST.in
README.md
requirements.txt
setup.py
pyauto/__init__.py
pyauto.local.egg-info/PKG-INFO
pyauto.local.egg-info/SOURCES.txt
pyauto.local.egg-info/dependency_links.txt
pyauto.local.egg-info/requires.txt
pyauto.local.egg-info/top_level.txt
pyauto/local/__init__.py
pyauto/local/commands.py
pyauto/local/config.py