Metadata-Version: 1.0
Name: pyauto.local
Version: 0.0.1
Summary: Helper functions for working with local files and templates
Home-page: UNKNOWN
Author: Adam Jaso
Author-email: UNKNOWN
License:                     GNU GENERAL PUBLIC LICENSE
